[
  {
    "id": "c1",
    "image": "../images/company/blvck.svg"
  },
  {
    "id": "c2",
    "image": "../images/company/bysl.svg"
  },
  {
    "id": "c3",
    "image": "../images/company/eversend.svg"
  },
  {
    "id": "c4",
    "image": "../images/company/feedly.svg"
  },
  {
    "id": "c5",
    "image": "../images/company/illiyeen.svg"
  },
  {
    "id": "c6",
    "image": "../images/company/legends.svg"
  },
  {
    "id": "c7",
    "image": "../images/company/synckloud.svg"
  },
  {
    "id": "c8",
    "image": "../images/company/zomato.svg"
  },
  {
    "id": "c9",
    "image": "../images/company/illiyeen.svg"
  },
  {
    "id": "c10",
    "image": "../images/company/blvck.svg"
  },
  {
    "id": "c11",
    "image": "../images/company/bysl.svg"
  },
  {
    "id": "c12",
    "image": "../images/company/eversend.svg"
  },
  {
    "id": "c13",
    "image": "../images/company/feedly.svg"
  },
  {
    "id": "c14",
    "image": "../images/company/synckloud.svg"
  },
  {
    "id": "c15",
    "image": "../images/company/zomato.svg"
  },
  {
    "id": "c16",
    "image": "../images/company/blvck.svg"
  },
  {
    "id": "c17",
    "image": "../images/company/bysl.svg"
  },
  {
    "id": "c18",
    "image": "../images/company/eversend.svg"
  },
  {
    "id": "c19",
    "image": "../images/company/feedly.svg"
  },
  {
    "id": "c20",
    "image": "../images/company/legends.svg"
  },
  {
    "id": "c21",
    "image": "../images/company/synckloud.svg"
  },
  {
    "id": "c22",
    "image": "../images/company/zomato.svg"
  },
  {
    "id": "c23",
    "image": "../images/company/blvck.svg"
  },
  {
    "id": "c24",
    "image": "../images/company/bysl.svg"
  }
]